clockpython.py
ClockPython-0.0.1.dist-info/LICENSE.txt
ClockPython-0.0.1.dist-info/METADATA
ClockPython-0.0.1.dist-info/WHEEL
ClockPython-0.0.1.dist-info/top_level.txt
ClockPython-0.0.1.dist-info/RECORD
