Metadata-Version: 2.1
Name: ClockPython
Version: 0.0.1
Summary: Gets the current 12 or 24 hour time
Home-page: https://github.com/gingerphoenix10/ClockPython
Author: gingerphoenix10
Author-email: gingerphoenix10@gmail.com
License: UNKNOWN
Platform: UNKNOWN
Classifier: Programming Language :: Python :: 3.10
Classifier: License :: OSI Approved :: GNU General Public License v2 or later (GPLv2+)
Classifier: Operating System :: OS Independent
License-File: LICENSE.txt
Provides-Extra: dev
Requires-Dist: pytest (>=3.7) ; extra == 'dev'
